falgopy/__init__.py
falgopy/algorithm/__init__.py
falgopy/algorithm/algorithm.py
falgopy/algorithm/algorithm_input.py
falgopy/algorithm/algorithm_output.py
falgopy/algorithm/utils.py
falgopy/scheduling/__init__.py
falgopy/scheduling/algorithms/__init__.py
falgopy/scheduling/algorithms/lottery/__init__.py
falgopy/scheduling/algorithms/round_robin/__init__.py
falgopy/scheduling/algorithms/round_robin/round_robin.py
falgopy/scheduling/algorithms/round_robin/round_robin_input.py
falgopy/scheduling/algorithms/round_robin/test_round_robin.py
falgopy/scheduling/scheduling_algorithm/__init__.py
falgopy/scheduling/scheduling_algorithm/scheduling_algorithm.py
falgopy/scheduling/scheduling_algorithm/scheduling_algorithm_input.py
falgopy/scheduling/scheduling_algorithm/scheduling_algorithm_output.py
falgopy/searching/__init__.py
falgopy/searching/algorithms/__init__.py
falgopy/searching/algorithms/binary_search/__init__.py
falgopy/searching/algorithms/binary_search/binary_search.py
falgopy/searching/algorithms/binary_search/test_binary_search.py
falgopy/searching/searching_algorithm/__init__.py
falgopy/searching/searching_algorithm/searching_algorithm.py
falgopy/searching/searching_algorithm/searching_algorithm_input.py
falgopy/searching/searching_algorithm/searching_algorithm_output.py
falgopy/sorting/__init__.py
falgopy/sorting/algorithms/__init__.py
falgopy/sorting/algorithms/insertion_sort/__init__.py
falgopy/sorting/algorithms/insertion_sort/insertion_sort.py
falgopy/sorting/algorithms/insertion_sort/test_insertion_sort.py
falgopy/sorting/algorithms/quick_sort/__init__.py
falgopy/sorting/algorithms/quick_sort/quick_sort.py
falgopy/sorting/algorithms/quick_sort/test_quick_sort.py
falgopy/sorting/sorting_algorithm/__init__.py
falgopy/sorting/sorting_algorithm/sorting_algorithm.py
falgopy/sorting/sorting_algorithm/sorting_algorithm_input.py
falgopy/sorting/sorting_algorithm/sorting_algorithm_output.py
falgopy/utils/__init__.py
falgopy/utils/logger/__init__.py
falgopy-3.0.0.dist-info/METADATA
falgopy-3.0.0.dist-info/WHEEL
falgopy-3.0.0.dist-info/top_level.txt
falgopy-3.0.0.dist-info/RECORD
