Metadata-Version: 2.1
Name: falgopy
Version: 3.0.0
Summary: A powerful falgopy package
Home-page: 
Author: Zohar franco
Author-email: 
Keywords: CS data data structures falgopy algo
Classifier: Intended Audience :: Developers
Classifier: Topic :: Software Development :: Build Tools
Classifier: Programming Language :: Python :: 3
